hotmailbox/__init__.py
hotmailbox/email.py
hotmailbox/errors.py
hotmailbox/stock.py
hotmailbox/translate.py
hotmailbox/user.py
hotmailbox.py-1.0.2.dist-info/LICENSE
hotmailbox.py-1.0.2.dist-info/METADATA
hotmailbox.py-1.0.2.dist-info/WHEEL
hotmailbox.py-1.0.2.dist-info/top_level.txt
hotmailbox.py-1.0.2.dist-info/RECORD
