Metadata-Version: 2.1
Name: hotmailbox.py
Version: 1.0.2
Summary: An API wrapper for hotmailbox.me written in Python.
Home-page: https://github.com/itschasa/hotmailbox.py
Author: itschasa
License: UNKNOWN
Platform: UNKNOWN
License-File: LICENSE
Requires-Dist: httpx
